[
    {
        "id": 1,
        "complete": false,
        "expired": false,
        "expiring": false,
        "title": "Prepare interview questions for tomorrow's meeting",
        "description": "Nostrud excepteur tempor laborum occaecat mollit Lorem anim pariatur in nulla.",
        "date": "2021-07-03",
        "category": "Interviews"
    },
    {
        "id": 2,
        "complete": false,
        "expired": false,
        "expiring": false,
        "title": "Book Greece",
        "description": "Nostrud excepteur tempor laborum occaecat mollit Lorem anim pariatur in nulla.",
        "date": "2021-09-13",
        "category": "Travel spots"
    },
    {
        "id": 3,
        "complete": false,
        "expired": false,
        "expiring": false,
        "title": "Buy some beer",
        "description": "Nostrud excepteur tempor laborum occaecat mollit Lorem anim pariatur in nulla.",
        "date": "2021-06-03",
        "category": "Shop lists"
    },
    {
        "id": 4,
        "complete": false,
        "expired": false,
        "expiring": false,
        "title": "Repair chair",
        "description": "Nostrud excepteur tempor laborum occaecat mollit Lorem anim pariatur in nulla.",
        "date": "2021-05-05",
        "category": "Home notes"
    },
    {
        "id": 5,
        "complete": false,
        "expired": false,
        "expiring": false,
        "title": "Buy new headphones",
        "description": "Nostrud excepteur tempor laborum occaecat mollit Lorem anim pariatur in nulla.",
        "date": "2021-06-20",
        "category": "Shop lists"
    }
]
